bmcore/__init__.py
bmcore/bmcollection.py
bmcore/bmenv.py
bmcore/bmmint.py
bmcore/bmsigner.py
bmcore/bmtypes.py
bmcore/bmvirtualwallet.py
bmcore-1.0.8.dist-info/LICENSE
bmcore-1.0.8.dist-info/METADATA
bmcore-1.0.8.dist-info/WHEEL
bmcore-1.0.8.dist-info/top_level.txt
bmcore-1.0.8.dist-info/RECORD
