Metadata-Version: 2.1
Name: bmcore
Version: 1.0.8
Summary: A set of utilities for Cardano NFTs built from pycardano
Home-page: https://github.com/pypa/sampleproject
Author: Mark Rufino
Author-email: mark.rufino.io@gmail.com
License: UNKNOWN
Project-URL: Bug Tracker, https://github.com/pypa/sampleproject/issues
Platform: UNKNOWN
Classifier: Programming Language :: Python :: 3
Classifier: License :: OSI Approved :: MIT License
Classifier: Operating System :: OS Independent
